{
  "experiment": "local_only",
  "node_name": "node_c",
  "hostname": "fedrgbd-c",
  "data_dir": "data/processed/non_iid_label/node_c",
  "epochs": 15,
  "batch_size": 8,
  "lr": 0.001,
  "seed": 42,
  "total_time_s": 3138.11,
  "final_test_loss": 0.033513,
  "final_test_accuracy": 0.992917,
  "cross_eval": {
    "node_a": {
      "test_loss": 0.058111,
      "test_accuracy": 0.988433
    },
    "node_b": {
      "test_loss": 0.066229,
      "test_accuracy": 0.985455
    }
  },
  "history": [
    {
      "epoch": 1,
      "train_loss": 0.091042,
      "val_loss": 0.050405,
      "val_accuracy": 0.983333,
      "epoch_time_s": 265.5
    },
    {
      "epoch": 2,
      "train_loss": 0.048858,
      "val_loss": 0.01213,
      "val_accuracy": 0.995833,
      "epoch_time_s": 204.0
    },
    {
      "epoch": 3,
      "train_loss": 0.045879,
      "val_loss": 0.022372,
      "val_accuracy": 0.993333,
      "epoch_time_s": 204.2
    },
    {
      "epoch": 4,
      "train_loss": 0.042676,
      "val_loss": 0.018452,
      "val_accuracy": 0.993333,
      "epoch_time_s": 205.8
    },
    {
      "epoch": 5,
      "train_loss": 0.03833,
      "val_loss": 0.011138,
      "val_accuracy": 0.995,
      "epoch_time_s": 204.8
    },
    {
      "epoch": 6,
      "train_loss": 0.028288,
      "val_loss": 0.025177,
      "val_accuracy": 0.992917,
      "epoch_time_s": 204.6
    },
    {
      "epoch": 7,
      "train_loss": 0.048699,
      "val_loss": 0.022786,
      "val_accuracy": 0.9925,
      "epoch_time_s": 204.6
    },
    {
      "epoch": 8,
      "train_loss": 0.027499,
      "val_loss": 0.012669,
      "val_accuracy": 0.995,
      "epoch_time_s": 204.5
    },
    {
      "epoch": 9,
      "train_loss": 0.032896,
      "val_loss": 0.025143,
      "val_accuracy": 0.992083,
      "epoch_time_s": 204.6
    },
    {
      "epoch": 10,
      "train_loss": 0.025508,
      "val_loss": 0.010502,
      "val_accuracy": 0.997083,
      "epoch_time_s": 205.3
    },
    {
      "epoch": 11,
      "train_loss": 0.026592,
      "val_loss": 0.044511,
      "val_accuracy": 0.99,
      "epoch_time_s": 205.3
    },
    {
      "epoch": 12,
      "train_loss": 0.029271,
      "val_loss": 0.013261,
      "val_accuracy": 0.994583,
      "epoch_time_s": 204.3
    },
    {
      "epoch": 13,
      "train_loss": 0.038305,
      "val_loss": 0.098415,
      "val_accuracy": 0.995417,
      "epoch_time_s": 207.7
    },
    {
      "epoch": 14,
      "train_loss": 0.024434,
      "val_loss": 0.018857,
      "val_accuracy": 0.995833,
      "epoch_time_s": 204.4
    },
    {
      "epoch": 15,
      "train_loss": 0.014407,
      "val_loss": 0.030835,
      "val_accuracy": 0.992917,
      "epoch_time_s": 208.5
    }
  ],
  "fl_round_equivalents": {
    "round_1": {
      "epoch": 5,
      "train_loss": 0.03833,
      "val_loss": 0.011138,
      "val_accuracy": 0.995,
      "epoch_time_s": 204.8
    },
    "round_2": {
      "epoch": 10,
      "train_loss": 0.025508,
      "val_loss": 0.010502,
      "val_accuracy": 0.997083,
      "epoch_time_s": 205.3
    },
    "round_3": {
      "epoch": 15,
      "train_loss": 0.014407,
      "val_loss": 0.030835,
      "val_accuracy": 0.992917,
      "epoch_time_s": 208.5
    }
  },
  "train_class_distribution": {
    "No_Fire": 8957,
    "Fire": 2240
  },
  "timestamp": "2026-04-02T00:04:48.592443"
}